Metadata-Version: 2.4
Name: automatyzer_desktop
Version: 0.1.8
Summary: Bot do automatyzacji zadań poprzez Remote Desktop
Home-page: https://github.com/automatyzer/desktop
Author: Tom Sapletta
Author-email: info@softreck.dev
License: MIT
Classifier: License :: OSI Approved :: MIT License
Classifier: Programming Language :: Python
Classifier: Programming Language :: Python :: 3
Classifier: Programming Language :: Python :: 3.7
Classifier: Programming Language :: Python :: 3.8
Classifier: Programming Language :: Python :: 3.9
Classifier: Programming Language :: Python :: 3.10
Classifier: Programming Language :: Python :: 3.11
Classifier: Programming Language :: Python :: Implementation :: CPython
Classifier: Programming Language :: Python :: Implementation :: PyPy
Requires-Python: >=3.7.0
License-File: LICENSE
Requires-Dist: python-dotenv>=0.21.0
Requires-Dist: psutil>=5.9.0
Requires-Dist: pyautogui>=0.9.53
Requires-Dist: pillow>=9.2.0
Requires-Dist: numpy>=1.23.0
Requires-Dist: opencv-python>=4.6.0
Requires-Dist: pytesseract>=0.3.10
Requires-Dist: pyperclip>=1.8.2
Requires-Dist: paramiko>=2.11.0
Requires-Dist: imaplib2>=3.6
Requires-Dist: email-validator>=1.2.1
Requires-Dist: pywinctl>=0.0.5
Provides-Extra: nlp
Requires-Dist: spacy>=3.4.0; extra == "nlp"
Requires-Dist: transformers>=4.24.0; extra == "nlp"
Requires-Dist: torch>=1.13.0; extra == "nlp"
Requires-Dist: SpeechRecognition>=3.8.1; extra == "nlp"
Requires-Dist: pyaudio>=0.2.12; extra == "nlp"
Requires-Dist: python-Levenshtein>=0.12.2; extra == "nlp"
Requires-Dist: tensorflow>=2.10.0; extra == "nlp"
Provides-Extra: data
Requires-Dist: pandas>=1.5.0; extra == "data"
Requires-Dist: matplotlib>=3.6.0; extra == "data"
Requires-Dist: seaborn>=0.12.0; extra == "data"
Requires-Dist: scikit-learn>=1.1.0; extra == "data"
Provides-Extra: test
Requires-Dist: pytest>=7.2.0; extra == "test"
Requires-Dist: pytest-cov>=4.0.0; extra == "test"
Requires-Dist: pytest-mock>=3.10.0; extra == "test"
Provides-Extra: dev
Requires-Dist: black; extra == "dev"
Requires-Dist: isort; extra == "dev"
Requires-Dist: flake8; extra == "dev"
Requires-Dist: mypy; extra == "dev"
Requires-Dist: pre-commit; extra == "dev"
Provides-Extra: all
Requires-Dist: spacy>=3.4.0; extra == "all"
Requires-Dist: transformers>=4.24.0; extra == "all"
Requires-Dist: torch>=1.13.0; extra == "all"
Requires-Dist: SpeechRecognition>=3.8.1; extra == "all"
Requires-Dist: pyaudio>=0.2.12; extra == "all"
Requires-Dist: python-Levenshtein>=0.12.2; extra == "all"
Requires-Dist: tensorflow>=2.10.0; extra == "all"
Requires-Dist: pandas>=1.5.0; extra == "all"
Requires-Dist: matplotlib>=3.6.0; extra == "all"
Requires-Dist: seaborn>=0.12.0; extra == "all"
Requires-Dist: scikit-learn>=1.1.0; extra == "all"
Requires-Dist: pytest>=7.2.0; extra == "all"
Requires-Dist: pytest-cov>=4.0.0; extra == "all"
Requires-Dist: pytest-mock>=3.10.0; extra == "all"
Requires-Dist: black; extra == "all"
Requires-Dist: isort; extra == "all"
Requires-Dist: flake8; extra == "all"
Requires-Dist: mypy; extra == "all"
Requires-Dist: pre-commit; extra == "all"
Dynamic: author
Dynamic: author-email
Dynamic: classifier
Dynamic: description
Dynamic: description-content-type
Dynamic: home-page
Dynamic: license
Dynamic: license-file
Dynamic: provides-extra
Dynamic: requires-dist
Dynamic: requires-python
Dynamic: summary
